Metadata-Version: 2.1
Name: nm-magic-wand
Version: 0.2.2
Summary: SparseLinear layers
Home-page: https://github.com/neuralmagic/magic_wand.git
Author: Neural Magic
Author-email: support@neuralmagic.com
License: Neural Magic Community License
Keywords: gpu sparsity compression
Classifier: Development Status :: 4 - Beta
Classifier: Topic :: Scientific/Engineering :: Artificial Intelligence
License-File: LICENSE
Requires-Dist: torch ==2.3.0
Requires-Dist: numpy
Requires-Dist: cmake >=3.21
Provides-Extra: dev
Requires-Dist: pre-commit ; extra == 'dev'
Requires-Dist: wheel ; extra == 'dev'
Requires-Dist: pytest ; extra == 'dev'
Requires-Dist: ruff ==0.1.5 ; extra == 'dev'
